__init__.py
motion_models_2d.py
motion_models_2d_torch.py
motion_models_3d.py
motion_models_3d_torch.py
test.py
test_torch.py
motion_models-0.0.8.dist-info/METADATA
motion_models-0.0.8.dist-info/WHEEL
motion_models-0.0.8.dist-info/top_level.txt
motion_models-0.0.8.dist-info/RECORD
