Metadata-Version: 2.1
Name: motion-models
Version: 0.0.8
Summary: Collection of motion models for 2D and 3D CT motion compensation
Author-email: Mareike Thies <mareike.thies@fau.de>
Classifier: Programming Language :: Python :: 3
Classifier: License :: OSI Approved :: MIT License
Classifier: Operating System :: OS Independent
Requires-Python: >=3.7
